MANIFEST.in
README
cydtw.c
cydtw.pyx
setup.py
cydtw.egg-info/PKG-INFO
cydtw.egg-info/SOURCES.txt
cydtw.egg-info/dependency_links.txt
cydtw.egg-info/requires.txt
cydtw.egg-info/top_level.txt