Metadata-Version: 1.0
Name: cydtw
Version: 0.1.4
Summary: DTW computation made efficient using Cython
Home-page: https://github.com/rtavenar/cydtw
Author: Romain Tavenard
Author-email: romain.tavenard@univ-rennes2.fr
License: UNKNOWN
Platform: UNKNOWN
